geoxgboost/__init__.py
geoxgboost/geoxgboost.py
geoxgboost-1.0.9.dist-info/LICENSE.txt
geoxgboost-1.0.9.dist-info/METADATA
geoxgboost-1.0.9.dist-info/WHEEL
geoxgboost-1.0.9.dist-info/top_level.txt
geoxgboost-1.0.9.dist-info/RECORD
