Metadata-Version: 2.1
Name: geoxgboost
Version: 1.0.9
Summary: Geographically Weighted XGBoost
Home-page: https://geoxgboost.readthedocs.io/
Author: George Grekousis
Author-email: geograik@gmail.com
License: MIT
Classifier: License :: OSI Approved :: MIT License
Classifier: Programming Language :: Python
Classifier: Programming Language :: Python :: 3.9
Classifier: Operating System :: OS Independent
Requires-Python: >=3.9
License-File: LICENSE.txt
Requires-Dist: pandas >=2.1.4
Requires-Dist: numpy >=1.26.4
Requires-Dist: scikit-learn >=1.4.2
Requires-Dist: scipy >=1.12.0
Requires-Dist: xgboost >=2.0
Requires-Dist: openpyxl >=3.0.9
